[
{
    "category": "Comics", 
    "description": "  「全巻無料で読み放題の女の子のためのNo1マンガアプリ」ess（エス）がついにリリース！", 
    "similar_apps": [
        "コミックエス - 少女漫画/恋愛マンガ 無料で読み放題♪", 
        "漫漫漫画-每日更新免费高清漫画", 
        "comico 免費全彩漫畫", 
        "漫咖", 
        "マンガ図書館Z　〜3800巻無料・読み放題のコミックアプリ！", 
        "漫畫神", 
        "腾讯动漫", 
        "漫本-全球华人原创漫画发行平台", 
        "LINE WEBTOON - Free Comics", 
        "【無料漫画】みんコミ/マンガ読み放題-美少女ヒロインいっぱい", 
        "LINE Manga -正版日本漫畫 每天免費更新！", 
        "COMIDEA    Writing Comics APP", 
        "ComicScreen - ComicViewer", 
        "[全巻無料] 奇面組 漫画を無料で読めるマンガコミックアプリ", 
        "Perfect Viewer"
    ], 
    "app_title": "GANMA! - 漫画が全話無料で制限ナシのマンガアプリ"
},{
    "category": "Comics", 
    "description": "  ＼ガンマンが登場するTVCM放映中!!／", 
    "similar_apps": [
        "GANMA! - 漫画が全話無料で制限ナシのマンガアプリ", 
        "コミックエス - 少女漫画/恋愛マンガ 無料で読み放題♪", 
        "【無料マンガ】マンガZERO／国内最大級の無料漫画アプリ", 
        "pixivコミック - みんなの無料マンガアプリ", 
        "マンガBANG！-人気漫画が全巻無料読み放題-", 
        "Manga Box: Manga App", 
        "マンガ図書館Z　〜3800巻無料・読み放題のコミックアプリ！", 
        "漫漫漫画-每日更新免费高清漫画", 
        "comico 免費全彩漫畫", 
        "【無料漫画】みんコミ/マンガ読み放題-美少女ヒロインいっぱい", 
        "漫本-全球华人原创漫画发行平台", 
        "腾讯动漫", 
        "漫咖", 
        "漫畫神", 
        "漫饭－随时随地看漫画"
    ], 
    "app_title": "漫画読破 全巻無料のマンガアプリ"
},{
    "category": "Comics", 
    "description": "  Genuine mobile phone serial wonderful animated comic novel, updated every day! ", 
    "similar_apps": [
        "漫咖", 
        "comico 免費全彩漫畫", 
        "漫漫漫画-每日更新免费高清漫画", 
        "LINE WEBTOON - Free Comics", 
        "漫畫神", 
        "漫本-全球华人原创漫画发行平台", 
        "LINE Manga -正版日本漫畫 每天免費更新！", 
        "GANMA! - 漫画が全話無料で制限ナシのマンガアプリ", 
        "コミックエス - 少女漫画/恋愛マンガ 無料で読み放題♪", 
        "COMIDEA    Writing Comics APP", 
        "极速漫画——免费看超有料的二次元阅读APP", 
        "台灣同人通", 
        "マンガ図書館Z　〜3800巻無料・読み放題のコミックアプリ！", 
        "네이버 웹툰 - Naver Webtoon", 
        "陰陽師漫畫大全 - 陰陽師之京都異變、陰陽師漫畫"
    ], 
    "app_title": "腾讯动漫"
},{
    "category": "Comics", 
    "description": "  HD Wallpaper Series with over 5,000,000+ Ultra HD free theme backgrounds. ", 
    "similar_apps": [
        "Cute Girl Anime Wallpaper HD", 
        "Anime Girl HD Wallpapers", 
        "DrawShow: Anime Manga Tutorial", 
        "Draw Anime - Manga Tutorials", 
        "Anime Couple Cute Wallpapers", 
        "Card Maker for YugiOh Duel TCG", 
        "Anime Girl Live Wallpapers", 
        "Anime Pictures", 
        "Crunchyroll - Everything Anime", 
        "Anime Avatar Studio", 
        "Langit Anime Mobile", 
        "Anime TV - animania kissanime", 
        "Anime Avatar -Unique Character", 
        "Avatar Maker: Anime", 
        "Anime GIFs"
    ], 
    "app_title": "HD Anime wallpapers"
},{
    "category": "Comics", 
    "description": "  Play Doh Superhero Kids Movies New Episodes! Spiderman Frozen Elsa Batman! ", 
    "similar_apps": [
        "FluffyJetToys", 
        "CKN Toys", 
        "Surprise Collector", 
        "FunToyzCollector", 
        "TMNT Comics", 
        "KidsSurpriseFun", 
        "Doh ToysReview", 
        "Paw Patrol by ShuffleCards", 
        "Crazy Fun Kids", 
        "DC Comics", 
        "Тест на Супергероя", 
        "Amazing Spider-Man 2 Keyboard", 
        "DisneyCarToys", 
        "Call From Paww Patrol", 
        "kids surprises"
    ], 
    "app_title": "kidsToysReview"
},{
    "category": "Comics", 
    "description": "  漫漫漫画，与优秀漫画作者倾情联袂，秉承正版原创，坚持每日首发，给你有笑意的条漫，有诚意的绘本，有新意的专题，最好不要错过。 ", 
    "similar_apps": [
        "漫漫漫画-每日更新免费高清漫画", 
        "漫咖", 
        "腾讯动漫", 
        "漫本-全球华人原创漫画发行平台", 
        "漫畫神", 
        "GANMA! - 漫画が全話無料で制限ナシのマンガアプリ", 
        "コミックエス - 少女漫画/恋愛マンガ 無料で読み放題♪", 
        "LINE Manga -正版日本漫畫 每天免費更新！", 
        "COMIDEA    Writing Comics APP", 
        "台灣同人通", 
        "陰陽師漫畫大全 - 陰陽師之京都異變、陰陽師漫畫", 
        "【無料漫画】みんコミ/マンガ読み放題-美少女ヒロインいっぱい", 
        "Boys' Love Comic–Cartoon&Anime", 
        "大渡漫畫APP", 
        "ComicScreen - ComicViewer"
    ], 
    "app_title": "极速漫画——免费看超有料的二次元阅读APP"
},{
    "category": "Comics", 
    "description": "  漫漫漫画，与优秀漫画作者倾情联袂，秉承正版原创，坚持每日首发，给你有笑意的条漫，有诚意的绘本，有新意的专题，最好不要错过。 ", 
    "similar_apps": [
        "漫漫漫画-每日更新免费高清漫画", 
        "漫咖", 
        "漫饭－随时随地看漫画", 
        "腾讯动漫", 
        "嗨漫画", 
        "邪恶漫画", 
        "COMIDEA    Writing Comics APP", 
        "超次元新番", 
        "動漫屋——快來免費閱讀漫畫、動畫", 
        "戀的故事-樹下繪本", 
        "コミックエス - 少女漫画/恋愛マンガ 無料で読み放題♪", 
        "乐看动漫", 
        "漫本-全球华人原创漫画发行平台", 
        "탑툰 - 웹툰/만화를 매일매일 무료", 
        "漫畫神"
    ], 
    "app_title": "多看漫画——多看优质免费的漫画"
},{
    "category": "Comics", 
    "description": "  Action, Adventure, in which blood Comics", 
    "similar_apps": [
        "comico 免費全彩漫畫", 
        "漫咖", 
        "GANMA! - 漫画が全話無料で制限ナシのマンガアプリ", 
        "漫漫漫画-每日更新免费高清漫画", 
        "漫畫神", 
        "腾讯动漫", 
        "漫本-全球华人原创漫画发行平台", 
        "LINE Manga -正版日本漫畫 每天免費更新！", 
        "コミックエス - 少女漫画/恋愛マンガ 無料で読み放題♪", 
        "极速漫画——免费看超有料的二次元阅读APP", 
        "COMIDEA    Writing Comics APP", 
        "陰陽師漫畫大全 - 陰陽師之京都異變、陰陽師漫畫", 
        "Boys' Love Comic–Cartoon&Anime", 
        "大渡漫畫APP", 
        "animeMANGA Reader for Dōjinshi"
    ], 
    "app_title": "台灣同人通"
},{
    "category": "Comics", 
    "description": "  Animal Theme by C Launcher for Android with Ice Wolf wallpaper &amazing icons! ", 
    "similar_apps": [
        "Ice Wolf Theme C Launcher", 
        "Pink Candy", 
        "Golden skull theme graffiti", 
        "Cat theme-Cute,Adorable,Lazy", 
        "Pink Love Bear Theme", 
        "Pink Panda Love", 
        "Little Lovers"
    ], 
    "app_title": "Pink Animals"
},{
    "category": "Comics", 
    "description": "  Personalize your phone with Pink Love Bear CM Launcher themes for FREE ", 
    "similar_apps": [
        "Pink Love Bear Theme", 
        "Cute Handwrite Cartoon Theme", 
        "Graffiti Art Show Theme", 
        "Sakura Flower", 
        "Black Technology Theme", 
        "Cool Black Theme", 
        "Cartoon Keyboard Theme", 
        "Funny Smile  Emoji", 
        "Snowflake Ice Frozen", 
        "Fashion Graffiti Street Art", 
        "Mini friends theme", 
        "Pink Princess Kitty", 
        "Cute Kitty Love Theme", 
        "White Theme", 
        "Cute Girl Theme"
    ], 
    "app_title": "Cat theme-Cute,Adorable,Lazy"
},{
    "category": "Comics", 
    "description": "  漫漫漫画，与优秀漫画作者倾情联袂，秉承正版原创，坚持每日首发，给你有笑意的条漫，有诚意的绘本，有新意的专题，最好不要错过。 ", 
    "similar_apps": [
        "漫漫漫画-每日更新免费高清漫画", 
        "漫咖", 
        "Secret Love - Dating game", 
        "腾讯动漫", 
        "漫本-全球华人原创漫画发行平台", 
        "LINE Manga -正版日本漫畫 每天免費更新！", 
        "GANMA! - 漫画が全話無料で制限ナシのマンガアプリ", 
        "漫畫神", 
        "コミックエス - 少女漫画/恋愛マンガ 無料で読み放題♪", 
        "COMIDEA    Writing Comics APP", 
        "陰陽師漫畫大全 - 陰陽師之京都異變、陰陽師漫畫", 
        "极速漫画——免费看超有料的二次元阅读APP", 
        "台灣同人通", 
        "Comic Browser- Cartoon & Anime", 
        "【無料漫画】みんコミ/マンガ読み放題-美少女ヒロインいっぱい"
    ], 
    "app_title": "Boys' Love Comic–Cartoon&Anime"
},{
    "category": "Comics", 
    "description": "  Action, Adventure, in which blood Comics", 
    "similar_apps": [
        "comico 免費全彩漫畫", 
        "漫漫漫画-每日更新免费高清漫画", 
        "LINE WEBTOON - Free Comics", 
        "漫畫神", 
        "腾讯动漫", 
        "LINE Manga -正版日本漫畫 每天免費更新！", 
        "漫本-全球华人原创漫画发行平台", 
        "GANMA! - 漫画が全話無料で制限ナシのマンガアプリ", 
        "コミックエス - 少女漫画/恋愛マンガ 無料で読み放題♪", 
        "COMIDEA    Writing Comics APP", 
        "Perfect Viewer", 
        "네이버 웹툰 - Naver Webtoon", 
        "极速漫画——免费看超有料的二次元阅读APP", 
        "マンガ図書館Z　〜3800巻無料・読み放題のコミックアプリ！", 
        "DrawShow: Anime Manga Tutorial"
    ], 
    "app_title": "漫咖"
},{
    "category": "Comics", 
    "description": "  Free comics are now available on your mobile devices! ", 
    "similar_apps": [
        "LINE WEBTOON - Free Comics", 
        "comico 免費全彩漫畫", 
        "漫咖", 
        "漫漫漫画-每日更新免费高清漫画", 
        "腾讯动漫", 
        "漫畫神", 
        "漫本-全球华人原创漫画发行平台", 
        "GANMA! - 漫画が全話無料で制限ナシのマンガアプリ", 
        "COMIDEA    Writing Comics APP", 
        "コミックエス - 少女漫画/恋愛マンガ 無料で読み放題♪", 
        "极速漫画——免费看超有料的二次元阅读APP", 
        "台灣同人通", 
        "네이버 웹툰 - Naver Webtoon", 
        "陰陽師漫畫大全 - 陰陽師之京都異變、陰陽師漫畫", 
        "Boys' Love Comic–Cartoon&Anime"
    ], 
    "app_title": "LINE Manga -正版日本漫畫 每天免費更新！"
},{
    "category": "Comics", 
    "description": "  ＼ガンマンが登場するTVCM放映中!!／", 
    "similar_apps": [
        "GANMA! - 漫画が全話無料で制限ナシのマンガアプリ", 
        "【無料マンガ】マンガZERO／国内最大級の無料漫画アプリ", 
        "コミックエス - 少女漫画/恋愛マンガ 無料で読み放題♪", 
        "pixivコミック - みんなの無料マンガアプリ", 
        "漫画読破 全巻無料のマンガアプリ", 
        "Manga Box: Manga App", 
        "マンガ図書館Z　〜3800巻無料・読み放題のコミックアプリ！", 
        "漫漫漫画-每日更新免费高清漫画", 
        "comico 免費全彩漫畫", 
        "【無料漫画】みんコミ/マンガ読み放題-美少女ヒロインいっぱい", 
        "漫本-全球华人原创漫画发行平台", 
        "漫畫神", 
        "腾讯动漫", 
        "漫咖", 
        "漫饭－随时随地看漫画"
    ], 
    "app_title": "マンガBANG！-人気漫画が全巻無料読み放題-"
},{
    "category": "Comics", 
    "description": "  ＼ガンマンが登場するTVCM放映中!!／", 
    "similar_apps": [
        "GANMA! - 漫画が全話無料で制限ナシのマンガアプリ", 
        "コミックエス - 少女漫画/恋愛マンガ 無料で読み放題♪", 
        "【無料マンガ】マンガZERO／国内最大級の無料漫画アプリ", 
        "マンガBANG！-人気漫画が全巻無料読み放題-", 
        "漫画読破 全巻無料のマンガアプリ", 
        "Manga Box: Manga App", 
        "マンガ図書館Z　〜3800巻無料・読み放題のコミックアプリ！", 
        "漫漫漫画-每日更新免费高清漫画", 
        "comico 免費全彩漫畫", 
        "【無料漫画】みんコミ/マンガ読み放題-美少女ヒロインいっぱい", 
        "漫本-全球华人原创漫画发行平台", 
        "腾讯动漫", 
        "漫畫神", 
        "漫咖", 
        "漫饭－随时随地看漫画"
    ], 
    "app_title": "pixivコミック - みんなの無料マンガアプリ"
},{
    "category": "Comics", 
    "description": "  Action, Adventure, in which blood Comics", 
    "similar_apps": [
        "comico 免費全彩漫畫", 
        "漫咖", 
        "漫漫漫画-每日更新免费高清漫画", 
        "腾讯动漫", 
        "漫本-全球华人原创漫画发行平台", 
        "漫畫神", 
        "极速漫画——免费看超有料的二次元阅读APP", 
        "LINE Manga -正版日本漫畫 每天免費更新！", 
        "GANMA! - 漫画が全話無料で制限ナシのマンガアプリ", 
        "コミックエス - 少女漫画/恋愛マンガ 無料で読み放題♪", 
        "COMIDEA    Writing Comics APP", 
        "台灣同人通", 
        "陰陽師漫畫大全 - 陰陽師之京都異變、陰陽師漫畫", 
        "大渡漫畫APP", 
        "TapTapToon"
    ], 
    "app_title": "東立電子書城"
},{
    "category": "Comics", 
    "description": "  Free comics are now available on your mobile devices! ", 
    "similar_apps": [
        "LINE WEBTOON - Free Comics", 
        "COMIDEA    Writing Comics APP", 
        "漫咖", 
        "漫漫漫画-每日更新免费高清漫画", 
        "comico 免費全彩漫畫", 
        "腾讯动漫", 
        "GANMA! - 漫画が全話無料で制限ナシのマンガアプリ", 
        "네이버 웹툰 - Naver Webtoon", 
        "コミックエス - 少女漫画/恋愛マンガ 無料で読み放題♪", 
        "LINE Manga -正版日本漫畫 每天免費更新！", 
        "【無料漫画】みんコミ/マンガ読み放題-美少女ヒロインいっぱい", 
        "ComiCat (Comic Reader/Viewer)", 
        "TapTapToon", 
        "comics", 
        "大渡漫畫APP"
    ], 
    "app_title": "Dream Flowers Girl"
},{
    "category": "Comics", 
    "description": "  reviewing kids toys and opening Giant SURPRISE EGG, Minions,Batman,Superman ", 
    "similar_apps": [
        "CKN Toys", 
        "Ryan ToysReview Video", 
        "Surprise Collector", 
        "Kiddyzuzaa", 
        "FluffyJetToys", 
        "Squish: Mickey Mouse Clubhouse", 
        "FunToyzCollector", 
        "Cars Tooned-Up Tales", 
        "KidsSurpriseFun", 
        "Doh ToysReview", 
        "kidsToysReview", 
        "Fans Of DisneyCarToys ✅", 
        "Disney Junior Magic Phone", 
        "Garage for Kids", 
        "Crazy Fun Kids"
    ], 
    "app_title": "DisneyCarToys"
},{
    "category": "Comics", 
    "description": "  Summer is over and school is back in session! Time to put on my thinking cap! ", 
    "similar_apps": [
        "Back to School - Hola Theme", 
        "LINE WEBTOON - Free Comics", 
        "ROMANCE", 
        "Forever Love You", 
        "New Komik Lucu Bikin Ngakak", 
        "Kolam Komik", 
        "Rage Comic Maker", 
        "Langit Anime Mobile", 
        "CIAYO Comics - Free Comics", 
        "NGOMIK - Baca Komik Indonesia", 
        "Comics", 
        "Bacamanga Lengkap", 
        "다음 웹툰 - Daum Webtoon", 
        "Komik Lucu Ngaco 4:Gokil", 
        "Komik Lucu Ngaco 3: Edan"
    ], 
    "app_title": "Pink Beauty Flowers Love"
},{
    "category": "Comics", 
    "description": "  Little Lovers will make your phone a brand new look! ", 
    "similar_apps": [
        "Little Lovers", 
        "Fashion Graffiti Street Art", 
        "Pink Panda Love", 
        "Funny Smile  Emoji", 
        "Pet Kitty", 
        "Pink Candy", 
        "Punk Panda", 
        "Pink Love Bear Theme", 
        "Romantic Love", 
        "Love Swan Colorful Lake", 
        "Cute Handwrite Cartoon Theme", 
        "ComiCat (Comic Reader/Viewer)", 
        "Hi you", 
        "Rage Comic Maker", 
        "LINE WEBTOON - Free Comics"
    ], 
    "app_title": "Hi Baby Girl"
},{
    "category": "Comics", 
    "description": "  Free comics are now available on your mobile devices! ", 
    "similar_apps": [
        "LINE WEBTOON - Free Comics", 
        "ROMANCE", 
        "Kolam Komik", 
        "New Komik Lucu Bikin Ngakak", 
        "CIAYO Comics - Free Comics", 
        "Komik Lucu Ngaco 4:Gokil", 
        "NGOMIK - Baca Komik Indonesia", 
        "네이버 웹툰 - Naver Webtoon", 
        "Komik Lucu Ngaco 3: Edan", 
        "Comics", 
        "Bacamanga Lengkap", 
        "BoBoiBoy On-the-go", 
        "Langit Anime Mobile", 
        "Rage Comic Maker", 
        "다음 웹툰 - Daum Webtoon"
    ], 
    "app_title": "Forever Love You"
},{
    "category": "Comics", 
    "description": "  Which is your favorite cartoon? learn to draw the glow cartoon step-by-step! ", 
    "similar_apps": [
        "Draw Glow Cartoon", 
        "Funny Smile Emoji Cartoon", 
        "Pink Cartoon Girl Love", 
        "DrawShow: Anime Manga Tutorial", 
        "Draw Cartoons 2", 
        "Colorful Fairy Tale Theme HD", 
        "LINE WEBTOON - Free Comics", 
        "Cute Handwrite Cartoon Theme", 
        "Cartoon,Avatar Maker", 
        "COMIDEA    Writing Comics APP", 
        "GANMA! - 漫画が全話無料で制限ナシのマンガアプリ", 
        "陰陽師漫畫大全 - 陰陽師之京都異變、陰陽師漫畫", 
        "comics", 
        "Honey Cartoon Theme", 
        "comico 免費全彩漫畫"
    ], 
    "app_title": "Cartoon Dream Animals"
},{
    "category": "Comics", 
    "description": "  Application and widget homesick and Kittens! Many written and spoken sentences! ", 
    "similar_apps": [
        "Seu Madruga Widget", 
        "Cats Widget", 
        "Lightsaber", 
        "Scanner Radio", 
        "Pose Tool 3D", 
        "comico 免費全彩漫畫", 
        "漫咖", 
        "漫漫漫画-每日更新免费高清漫画", 
        "LINE WEBTOON - Free Comics", 
        "漫畫神", 
        "LINE Manga -正版日本漫畫 每天免費更新！", 
        "腾讯动漫", 
        "漫本-全球华人原创漫画发行平台", 
        "GANMA! - 漫画が全話無料で制限ナシのマンガアプリ", 
        "陰陽師漫畫大全 - 陰陽師之京都異變、陰陽師漫畫"
    ], 
    "app_title": "Zodiac sign Clock Widget"
},{
    "category": "Comics", 
    "description": "  We collect Surprise Eggs such as Kinder Surprise which have fun toys inside. ", 
    "similar_apps": [
        "Surprise Collector", 
        "New Barbie Doll Videos", 
        "DisneyCarToys", 
        "حكايات ما احلاها بدون نت", 
        "أغانى أطفال بيبى - بدون أنترنت", 
        "Cinderella Story VIDEOs", 
        "FluffyJetToys", 
        "Cookieswirlc Fans", 
        "CKN Toys", 
        "Amazing Spider-Man 2 Keyboard", 
        "Stylish Dressup", 
        "Marvel Comics", 
        "Talking Pretty Girl", 
        "kidsToysReview", 
        "Marvel Unlimited"
    ], 
    "app_title": "Kiddyzuzaa"
},{
    "category": "Comics", 
    "description": "  Pink Panda Love will make your phone a brand new look! ", 
    "similar_apps": [
        "Pink Panda Love", 
        "Funny Smile  Emoji", 
        "Fashion Graffiti Street Art", 
        "Cool Black Theme", 
        "Black Technology Theme", 
        "Cute Owl Keyboard Changer", 
        "Pet Kitty", 
        "Pink Candy", 
        "Theme for Samsung S8 Plus", 
        "Hi Baby Girl", 
        "Punk Panda", 
        "Pink Gold Diamond Live Theme", 
        "Romantic Love", 
        "Pink Love Bear Theme", 
        "Cartoon Keyboard Theme"
    ], 
    "app_title": "Little Lovers"
},{
    "category": "Comics", 
    "description": "  ComicScreen can show manga images, photos and comics pictures in compressed file ", 
    "similar_apps": [
        "ComicScreen - ComicViewer", 
        "Challenger Comics Viewer", 
        "Astonishing Comic Reader", 
        "Comics Reader: CBR, CBZ, PDF", 
        "ComiCat (Comic Reader/Viewer)", 
        "Comics", 
        "ComicRack Free", 
        "Marvel Unlimited", 
        "LINE WEBTOON - Free Comics", 
        "Marvel Comics", 
        "Perfect Viewer PDF&DJVU Plugin", 
        "DC Comics", 
        "Dark Horse Comics", 
        "SCViewer (Scan-manga viewer)", 
        "Maru"
    ], 
    "app_title": "Perfect Viewer"
},{
    "category": "Comics", 
    "description": "  Learn how to draw anime & cartoon step by step with animated strokes tutorial. ", 
    "similar_apps": [
        "DrawShow: Anime Manga Tutorial", 
        "comico 免費全彩漫畫", 
        "Cartoonist Free - Cartoon, Ani", 
        "漫漫漫画-每日更新免费高清漫画", 
        "漫咖", 
        "LINE WEBTOON - Free Comics", 
        "腾讯动漫", 
        "GANMA! - 漫画が全話無料で制限ナシのマンガアプリ", 
        "LINE Manga -正版日本漫畫 每天免費更新！", 
        "漫畫神", 
        "漫本-全球华人原创漫画发行平台", 
        "Expressive Comic Creator", 
        "コミックエス - 少女漫画/恋愛マンガ 無料で読み放題♪", 
        "极速漫画——免费看超有料的二次元阅读APP", 
        "Rage Comic Maker"
    ], 
    "app_title": "COMIDEA    Writing Comics APP"
},{
    "category": "Comics", 
    "description": "  New wallpapers app with more than 10000 beautiful pictures of anime ", 
    "similar_apps": [
        "HD Anime wallpapers", 
        "Cute Girl Anime Wallpaper HD", 
        "DrawShow: Anime Manga Tutorial", 
        "Draw Anime - Manga Tutorials", 
        "Anime Girl Wallpaper HD", 
        "Anime Girl Live Wallpapers", 
        "Anime Couple Cute Wallpapers", 
        "安眠ひざまくら　～就寝５分前の癒しタイム～　白崎楓ver", 
        "ワガハイタッチ！", 
        "Anime Avatar Studio", 
        "LINE WEBTOON - Free Comics", 
        "Kiss of Revenge", 
        "Anime Girl", 
        "Anime Pictures", 
        "Langit Anime Mobile"
    ], 
    "app_title": "Anime Girl HD Wallpapers"
},{
    "category": "Comics", 
    "description": "  Little Lovers will make your phone a brand new look! ", 
    "similar_apps": [
        "Little Lovers", 
        "Fashion Graffiti Street Art", 
        "Pink Panda Love", 
        "Funny Smile  Emoji", 
        "Pink Candy", 
        "Hi Baby Girl", 
        "Punk Panda", 
        "Pink Love Bear Theme", 
        "LINE WEBTOON - Free Comics", 
        "COMIDEA    Writing Comics APP", 
        "네이버 웹툰 - Naver Webtoon", 
        "GANMA! - 漫画が全話無料で制限ナシのマンガアプリ", 
        "漫咖", 
        "comico 免費全彩漫畫", 
        "漫漫漫画-每日更新免费高清漫画"
    ], 
    "app_title": "Pet Kitty"
},{
    "category": "Comics", 
    "description": "  New wallpapers app with more than 10000 beautiful pictures of anime ", 
    "similar_apps": [
        "HD Anime wallpapers", 
        "Anime Girl HD Wallpapers", 
        "Anime Girl Live Wallpapers", 
        "Anime Couple Cute Wallpapers", 
        "Anime Girl Wallpaper HD", 
        "Anime Pictures", 
        "DrawShow: Anime Manga Tutorial", 
        "Anime Girl Wallpaper", 
        "Draw Anime - Manga Tutorials", 
        "Anime Avatar Studio", 
        "Anime Girl", 
        "Langit Anime Mobile", 
        "Anime Notify", 
        "Anime Wallpaper HD", 
        "Anime Wallpapers Free HD"
    ], 
    "app_title": "Cute Girl Anime Wallpaper HD"
},{
    "category": "Comics", 
    "description": "  Download the custom keyboard for the new blockbuster: The Amazing Spider-Man 2! ", 
    "similar_apps": [
        "Amazing Spider-Man 2 Keyboard", 
        "FluffyJetToys", 
        "Ranger Toys", 
        "SuperHero VS SuperHero", 
        "DisneyCarToys", 
        "Power Rangers Sticker Share", 
        "Power Rangers Command Center", 
        "kidsToysReview", 
        "Toys Ranger", 
        "Green Ranger", 
        "DC Comics", 
        "Marvel Comics", 
        "Mix+Smash: Marvel Mashers", 
        "Pocket Heroes Mod & Skins MCPE", 
        "Guide batman return to arkham"
    ], 
    "app_title": "CKN Toys"
},{
    "category": "Comics", 
    "description": "  HD Wallpaper Series with over 5,000,000+ Ultra HD free theme backgrounds. ", 
    "similar_apps": [
        "Cute Girl Anime Wallpaper HD", 
        "HD Anime wallpapers", 
        "Anime Girl HD Wallpapers", 
        "Anime Girl Live Wallpapers", 
        "DrawShow: Anime Manga Tutorial", 
        "Draw Anime - Manga Tutorials", 
        "Langit Anime Mobile", 
        "Anime Avatar Studio", 
        "Anime Girl Wallpaper HD", 
        "Anime Pictures", 
        "Anime Girl", 
        "Anime Sweet Couple in Love", 
        "Anime Notify", 
        "LINE WEBTOON - Free Comics", 
        "Anime Alone Guy Wallpapers"
    ], 
    "app_title": "Anime Couple Cute Wallpapers"
},{
    "category": "Comics", 
    "description": "  fun, HD videos playing with toys and opening giant surprise eggs. ever, ", 
    "similar_apps": [
        "Kiddyzuzaa", 
        "KidsSurpriseFun", 
        "DisneyCarToys", 
        "FluffyJetToys", 
        "kidsToysReview", 
        "FunToyzCollector", 
        "Doh ToysReview", 
        "CKN Toys", 
        "Crazy Fun Kids", 
        "New Barbie Doll Videos", 
        "My Little Pony Comics", 
        "kids surprises", 
        "حكايات ما احلاها بدون نت", 
        "Toy Trains", 
        "Cinderella Story VIDEOs"
    ], 
    "app_title": "Surprise Collector"
},{
    "category": "Comics", 
    "description": "  ＼ガンマンが登場するTVCM放映中!!／", 
    "similar_apps": [
        "GANMA! - 漫画が全話無料で制限ナシのマンガアプリ", 
        "マンガ図書館Z　〜3800巻無料・読み放題のコミックアプリ！", 
        "漫漫漫画-每日更新免费高清漫画", 
        "comico 免費全彩漫畫", 
        "【無料漫画】みんコミ/マンガ読み放題-美少女ヒロインいっぱい", 
        "腾讯动漫", 
        "漫畫神", 
        "漫本-全球华人原创漫画发行平台", 
        "漫咖", 
        "LINE WEBTOON - Free Comics", 
        "[全巻無料] 奇面組 漫画を無料で読めるマンガコミックアプリ", 
        "完全無料!!スラムダンクの続き(まとめサイト)新着782話", 
        "ComicScreen - ComicViewer", 
        "COMIDEA    Writing Comics APP", 
        "极速漫画——免费看超有料的二次元阅读APP"
    ], 
    "app_title": "コミックエス - 少女漫画/恋愛マンガ 無料で読み放題♪"
},{
    "category": "Comics", 
    "description": "  where we show Play-Doh Clay, surprise eggs, candies, Angry Birds, Chocolate Toys ", 
    "similar_apps": [
        "KidsSurpriseFun", 
        "ComiCat (Comic Reader/Viewer)", 
        "KidsToysToSee", 
        "LINE WEBTOON - Free Comics", 
        "GANMA! - 漫画が全話無料で制限ナシのマンガアプリ", 
        "Marvel Comics", 
        "DC Comics", 
        "comics", 
        "Kiddyzuzaa", 
        "comico 免費全彩漫畫", 
        "漫咖", 
        "Perfect Viewer", 
        "Rage Comic Maker", 
        "漫漫漫画-每日更新免费高清漫画", 
        "漫本-全球华人原创漫画发行平台"
    ], 
    "app_title": "Baby Big Mouth"
},{
    "category": "Comics", 
    "description": "  Genuine mobile phone serial wonderful animated comic novel, updated every day! ", 
    "similar_apps": [
        "漫咖", 
        "腾讯动漫", 
        "漫漫漫画-每日更新免费高清漫画", 
        "漫本-全球华人原创漫画发行平台", 
        "漫畫神", 
        "GANMA! - 漫画が全話無料で制限ナシのマンガアプリ", 
        "コミックエス - 少女漫画/恋愛マンガ 無料で読み放題♪", 
        "LINE Manga -正版日本漫畫 每天免費更新！", 
        "极速漫画——免费看超有料的二次元阅读APP", 
        "COMIDEA    Writing Comics APP", 
        "台灣同人通", 
        "Boys' Love Comic–Cartoon&Anime", 
        "【無料漫画】みんコミ/マンガ読み放題-美少女ヒロインいっぱい", 
        "大渡漫畫APP", 
        "東立電子書城"
    ], 
    "app_title": "陰陽師漫畫大全 - 陰陽師之京都異變、陰陽師漫畫"
},{
    "category": "Comics", 
    "description": "  Little Lovers will make your phone a brand new look! ", 
    "similar_apps": [
        "Little Lovers", 
        "Funny Smile  Emoji", 
        "Fashion Graffiti Street Art", 
        "Black Technology Theme", 
        "Cool Black Theme", 
        "Pet Kitty", 
        "Cute Owl Keyboard Changer", 
        "Pink Candy", 
        "Punk Panda", 
        "Theme for Samsung S8 Plus", 
        "Hi Baby Girl", 
        "Pink Love Bear Theme", 
        "Pink Gold Diamond Live Theme", 
        "Baby Panda", 
        "Cartoon Keyboard Theme"
    ], 
    "app_title": "Pink Panda Love"
},{
    "category": "Comics", 
    "description": "  Cat theme is free for your android phone. ", 
    "similar_apps": [
        "Cat theme-Cute,Adorable,Lazy", 
        "Cool Black Theme", 
        "Black Technology Theme", 
        "Cartoon Keyboard Theme", 
        "White Theme", 
        "Cute Owl Keyboard Changer", 
        "Fast Theme", 
        "Sakura Flower", 
        "Cute Handwrite Cartoon Theme", 
        "Spring Flowers Theme", 
        "Pink Princess Kitty", 
        "Fashion Graffiti Street Art", 
        "Pink Glitter Keyboard Themes", 
        "Theme for Samsung J7", 
        "Theme for Samsung S8 Plus"
    ], 
    "app_title": "Pink Love Bear Theme"
},{
    "category": "Comics", 
    "description": "  kids toys review for toddlers,babies, infants,Pixar, Nickelodeon, Play Doh ", 
    "similar_apps": [
        "Kids Toys", 
        "PlayToys Review", 
        "ToysCollector", 
        "Dora and Friends", 
        "Superhero & Princess Kids IRL", 
        "Map Spongebob Addon for MCPE", 
        "Bikini Bob Maps Mods for MCPE", 
        "Bikini Bob Maps Mods for MCPE", 
        "Nickelodeon The Splat Emojis", 
        "Doh ToysReview", 
        "FluffyJetToys", 
        "kidsToysReview", 
        "Surprise Collector", 
        "KidsSurpriseFun", 
        "Crazy Fun Kids"
    ], 
    "app_title": "KidsToysAndMe"
},{
    "category": "Comics", 
    "description": "  Over 1,000,000 SPHD Anime & Cartoon Comic Anime Girls HD Wallpaper! ", 
    "similar_apps": [
        "Anime Girls HD Wallpaper", 
        "Anime Girls All HD", 
        "Anime Girls Best", 
        "Anime Girls", 
        "Anime Girls HD", 
        "Anime Girls Cute", 
        "Anime Girls Pro", 
        "Anime Girl Wallpaper", 
        "Anime Girls Full HD", 
        "Anime Girls Wallpaper HD", 
        "Anime Girls Background", 
        "Anime Girls Wallpaper", 
        "Princess Girl Wallpaper HD", 
        "Anime Pictures", 
        "Anime Wallpaper HD"
    ], 
    "app_title": "Anime Girls Otaku Wallpaper"
},{
    "category": "Comics", 
    "description": "  Over 1,000,000 SPHD Anime & Cartoon Comic Anime Girls HD! ", 
    "similar_apps": [
        "Anime Girls HD", 
        "Anime Girls All HD", 
        "Princess Girl Wallpaper HD", 
        "Anime Girls Best", 
        "Anime Girls HD Wallpaper", 
        "Anime Girls Pro", 
        "Anime Girls", 
        "Anime Pictures", 
        "Anime Girls Full HD", 
        "Anime Girls Background", 
        "An Anime Girls", 
        "Anime HD Backgrounds Pro", 
        "Anime Girls Full", 
        "Anime Girl Pose 3D", 
        "Anime Girls Otaku Wallpaper"
    ], 
    "app_title": "Anime Girls Cute"
},{
    "category": "Comics", 
    "description": "  we will public about  surprise eggs, play doh, play doh ice cream videos ", 
    "similar_apps": [
        "Doh ToysReview", 
        "FluffyJetToys", 
        "Crazy Fun Kids", 
        "kids surprises", 
        "Playing Dough Reviews", 
        "Kids Toys", 
        "Kids Toys collection", 
        "PlayToys Review", 
        "Surprise Eggs unboxing toys", 
        "Ryan ToysReview Video", 
        "KidsToysAndMe", 
        "FunToyzCollector Kids", 
        "Play WithToy", 
        "Dough Toys", 
        "Superhero Fun Kids Stop Motion"
    ], 
    "app_title": "Play Toy Surprises"
},{
    "category": "Comics", 
    "description": "  Over 1,000,000 SPHD Anime & Cartoon Comic Anime Girls HD! ", 
    "similar_apps": [
        "Anime Girls HD", 
        "Anime Girls Cute", 
        "Anime Girls All HD", 
        "Anime Girls HD Wallpaper", 
        "Anime Girls Full HD", 
        "Princess Girl Wallpaper HD", 
        "Anime Girls Best", 
        "Anime Girls", 
        "Anime Girls Background", 
        "Anime Girls Full", 
        "Anime HD Backgrounds Pro", 
        "Anime Girls Otaku Wallpaper", 
        "An Anime Girls", 
        "Anime Pictures", 
        "Anime Girls Wallpaper HD"
    ], 
    "app_title": "Anime Girls Pro"
},{
    "category": "Comics", 
    "description": "  Over 1,000,000 SPHD Anime & Cartoon Comic Anime Girls HD! ", 
    "similar_apps": [
        "Anime Girls HD", 
        "Anime Girls All HD", 
        "Anime Girls HD Wallpaper", 
        "Anime Girls Cute", 
        "Anime Girls Best", 
        "Princess Girl Wallpaper HD", 
        "Anime Girls Pro", 
        "Anime Girls", 
        "Anime Girls Full", 
        "Anime Girls Background", 
        "Anime Girls Otaku Wallpaper", 
        "Anime HD Backgrounds Pro", 
        "Anime Girls Wallpaper HD", 
        "Anime Pictures", 
        "Anime Girls Wallpaper"
    ], 
    "app_title": "Anime Girls Full HD"
},{
    "category": "Comics", 
    "description": "  Real Followers 3500 ++ Pro ", 
    "similar_apps": [
        "Real Followers 3500 ++ Pro", 
        "Get Real Followers", 
        "Get Followers for Insta", 
        "Boost Instagram Followers Tips", 
        "Real Followers For IG Prank", 
        "R‍eal fol‍low‍ers 100% prank", 
        "Followers For Funimate"
    ], 
    "app_title": "Get Followers 4500 ++ Pro"
},{
    "category": "Comics", 
    "description": "  New wallpapers app with more than 10000 beautiful pictures of anime ", 
    "similar_apps": [
        "HD Anime wallpapers", 
        "Tips Yu-Gi-Oh Trading Card", 
        "Yugipedia: YuGiOh Deck Builder", 
        "Card Maker for Pokemon", 
        "YgoDeck - Manager for Yugioh", 
        "Life Points LITE for YuGiOh", 
        "Card Maker for YugiOh Duel TCG", 
        "Lp Counter YuGiOh Free", 
        "YugiDuel: YuGiOh LP Calc Free", 
        "Cyber Duelist News", 
        "Deckmaker for Yu-Gi-Oh!", 
        "Guide for Yu-Gi-Oh! Duel Links", 
        "Wishlist for YuGiOh! Pro", 
        "Rage Comic Maker", 
        "Comic Creator"
    ], 
    "app_title": "Card Maker for YugiOh Duel TCG"
},{
    "category": "Comics", 
    "description": "  Action, Adventure, in which blood Comics", 
    "similar_apps": [
        "comico 免費全彩漫畫", 
        "LINE WEBTOON - Free Comics", 
        "漫咖", 
        "漫漫漫画-每日更新免费高清漫画", 
        "漫畫神", 
        "腾讯动漫", 
        "LINE Manga -正版日本漫畫 每天免費更新！", 
        "漫本-全球华人原创漫画发行平台", 
        "GANMA! - 漫画が全話無料で制限ナシのマンガアプリ", 
        "极速漫画——免费看超有料的二次元阅读APP", 
        "コミックエス - 少女漫画/恋愛マンガ 無料で読み放題♪", 
        "네이버 웹툰 - Naver Webtoon", 
        "台灣同人通", 
        "COMIDEA    Writing Comics APP", 
        "陰陽師漫畫大全 - 陰陽師之京都異變、陰陽師漫畫"
    ], 
    "app_title": "B.Duck TouchPal Sticker"
},{
    "category": "Comics", 
    "description": "  kids toys review for toddlers,babies, infants,Pixar, Nickelodeon, Play Doh ", 
    "similar_apps": [
        "Kids Toys", 
        "PlayToys Review", 
        "ToysCollector", 
        "KidsToysAndMe", 
        "kids surprises", 
        "Doh ToysReview", 
        "KidsSurpriseFun", 
        "kidsToysReview", 
        "Crazy Fun Kids", 
        "Surprise Collector", 
        "DisneyCarToys", 
        "FluffyJetToys", 
        "Playing Dough Reviews", 
        "FunToyzCollector Kids", 
        "FunToysReview"
    ], 
    "app_title": "KidsFunToys"
},{
    "category": "Comics", 
    "description": "  App for fujoshis and fundashis lovers of Yaoi. Wear yaoi on your cell phone. ", 
    "similar_apps": [
        "Yaoi Manga", 
        "Yaoi Manga Brasileiro", 
        "やおい - Yaoi", 
        "Yaoi Manga Français", 
        "야오이 엔 코아 난 - Yaoi in Korean", 
        "Yaoi Addicted", 
        "Boys' Love Comic–Cartoon&Anime", 
        "Doujinshi Yaoi Online", 
        "My Lovely Cat (Esp)", 
        "Crunchyroll Manga", 
        "Mangaa Reader", 
        "Let's Shojo Vol.1", 
        "Anime Keyboard Theme", 
        "Romance en Escuela Encantada", 
        "Yaoi Images"
    ], 
    "app_title": "yaoi ในไทย"
},{
    "category": "Comics", 
    "description": "  Over 1,000,000 SPHD Anime & Cartoon Comic Anime Girls HD! ", 
    "similar_apps": [
        "Anime Girls HD", 
        "Anime Girls Cute", 
        "Anime Girls All HD", 
        "Anime Girls Best", 
        "Anime Girls HD Wallpaper", 
        "Anime Girls Full HD", 
        "Anime Girl Pose 3D", 
        "Anime Girls Pro", 
        "Anime Girls Background", 
        "Princess Girl Wallpaper HD", 
        "Anime HD Backgrounds Pro", 
        "Anime Girls Otaku Wallpaper", 
        "Anime Girls Full", 
        "Anime Girl Wallpaper", 
        "An Anime Girls"
    ], 
    "app_title": "Anime Girls"
},{
    "category": "Comics", 
    "description": "  Sword or Art Online of the mystery of Gaiden Mothers Rosary you can be solved! ? ", 
    "similar_apps": [
        "QuizForソードアートオンラインSAOマザーズ・ロザリオ"
    ], 
    "app_title": "HD wallpapers For Sword Art"
},{
    "category": "Comics", 
    "description": "  Over 1,000,000 SPHD Anime & Cartoon Comic Anime Girls HD! ", 
    "similar_apps": [
        "Anime Girls HD", 
        "Anime Girls Cute", 
        "Anime Girls Best", 
        "Anime Girls All HD", 
        "Anime Girls Pro", 
        "Anime Girls", 
        "Princess Girl Wallpaper HD", 
        "Anime HD Backgrounds Pro", 
        "Anime Girls HD Wallpaper", 
        "Anime Girls Full", 
        "Anime Girls Full HD", 
        "Anime Girls Otaku Wallpaper", 
        "Anime Girl Wallpaper", 
        "Anime Pictures", 
        "An Anime Girls"
    ], 
    "app_title": "Anime Girls Background"
},{
    "category": "Comics", 
    "description": "  Superhero Vidoes is the best application for kids with superheroes in real life ", 
    "similar_apps": [
        "Superhero & Princess for Kids"
    ], 
    "app_title": "SuperheroKidsEpisodes"
},{
    "category": "Comics", 
    "description": "  we will public about  surprise eggs, play doh, play doh ice cream videos ", 
    "similar_apps": [
        "Doh ToysReview", 
        "kidsToysReview", 
        "Surprise Collector", 
        "Crazy Fun Kids", 
        "FluffyJetToys", 
        "Playing Dough Reviews", 
        "DisneyCarToys", 
        "kids surprises", 
        "Kids Toys", 
        "Kids Toys collection", 
        "FunToyzCollector Kids", 
        "Play Toy Surprises", 
        "Play WithToy", 
        "PlayToys Review", 
        "KidsFunToys"
    ], 
    "app_title": "FunToysReview"
},{
    "category": "Comics", 
    "description": "  Over 1,000,000 SPHD Anime & Cartoon Comic Anime Girls HD! ", 
    "similar_apps": [
        "Anime Girls HD", 
        "Anime Girls All HD", 
        "Anime Girls Cute", 
        "COMIDEA    Writing Comics APP", 
        "Anime Girls", 
        "Anime Girls Background", 
        "Anime Girls Best", 
        "Anime Girls Full", 
        "Anime Manga Drawing", 
        "Anime Maker", 
        "Anime Girls HD Wallpaper", 
        "Anime Girls Pro", 
        "Princess Girl Wallpaper HD", 
        "Anime Girls Full HD", 
        "An Anime Girls"
    ], 
    "app_title": "Anime HD Backgrounds Pro"
},{
    "category": "Comics", 
    "description": "  漫漫漫画，与优秀漫画作者倾情联袂，秉承正版原创，坚持每日首发，给你有笑意的条漫，有诚意的绘本，有新意的专题，最好不要错过。 ", 
    "similar_apps": [
        "漫漫漫画-每日更新免费高清漫画", 
        "comico 免費全彩漫畫", 
        "漫咖", 
        "Manga Box: Manga App", 
        "漫饭－随时随地看漫画", 
        "腾讯动漫", 
        "動漫屋——快來免費閱讀漫畫、動畫", 
        "漫畫神", 
        "嗨漫画", 
        "漫本-全球华人原创漫画发行平台", 
        "GANMA! - 漫画が全話無料で制限ナシのマンガアプリ", 
        "LINE Manga -正版日本漫畫 每天免費更新！", 
        "Comics4Me", 
        "COMIDEA    Writing Comics APP", 
        "コミックエス - 少女漫画/恋愛マンガ 無料で読み放題♪"
    ], 
    "app_title": "邪恶漫画"
},{
    "category": "Comics", 
    "description": "  toy review for toddlers,babies, infants,Pixar, Nickelodeon, Play Doh, Claymation ", 
    "similar_apps": [
        "FunToyzCollector", 
        "Doh ToysReview", 
        "Surprise Collector", 
        "kidsToysReview", 
        "Pink Princess Kitty", 
        "FluffyJetToys", 
        "Hello Kitty StoryGIF", 
        "Crazy Fun Kids", 
        "PLAYDOHCards by Shuffle", 
        "Dough Toys", 
        "Baby Big Mouth", 
        "ToonsTV: Angry Birds video app", 
        "Guide New Angry Bird 2", 
        "DisneyCarToys", 
        "kids surprises"
    ], 
    "app_title": "KidsSurpriseFun"
},{
    "category": "Comics", 
    "description": "  we will public about  surprise eggs, play doh, play doh ice cream videos ", 
    "similar_apps": [
        "Doh ToysReview", 
        "KidsSurpriseFun", 
        "Kids Toys", 
        "Dora and Friends", 
        "Dough Toys", 
        "kidsToysReview", 
        "PlayToys Review", 
        "Surprise Collector", 
        "FluffyJetToys", 
        "Bikini Bob Maps Minecraft PE", 
        "PLAYDOHCards by Shuffle", 
        "Map Spongebob Addon for MCPE", 
        "kids surprises", 
        "Crazy Fun Kids", 
        "CKN Toys"
    ], 
    "app_title": "FunToyzCollector"
},{
    "category": "Comics", 
    "description": "  Action, Adventure, in which blood Comics", 
    "similar_apps": [
        "comico 免費全彩漫畫", 
        "GANMA! - 漫画が全話無料で制限ナシのマンガアプリ", 
        "漫漫漫画-每日更新免费高清漫画", 
        "漫咖", 
        "LINE WEBTOON - Free Comics", 
        "【無料マンガ】マンガZERO／国内最大級の無料漫画アプリ", 
        "コミックエス - 少女漫画/恋愛マンガ 無料で読み放題♪", 
        "pixivコミック - みんなの無料マンガアプリ", 
        "マンガBANG！-人気漫画が全巻無料読み放題-", 
        "漫画読破 全巻無料のマンガアプリ", 
        "漫畫神", 
        "腾讯动漫", 
        "漫饭－随时随地看漫画", 
        "漫本-全球华人原创漫画发行平台", 
        "LINE Manga -正版日本漫畫 每天免費更新！"
    ], 
    "app_title": "Manga Box: Manga App"
},{
    "category": "Comics", 
    "description": "  ComiCat is the top rated comic reader and catalog manager for Android. ", 
    "similar_apps": [
        "ComiCat (Comic Reader/Viewer)", 
        "LINE WEBTOON - Free Comics", 
        "Marvel Comics", 
        "Perfect Viewer", 
        "comics", 
        "KidsSurpriseFun", 
        "Comics", 
        "ComicScreen - ComicViewer", 
        "DC Comics", 
        "Challenger Comics Viewer", 
        "CIAYO Comics - Free Comics", 
        "Marvel Unlimited", 
        "Dark Horse Comics", 
        "ComicRack Free", 
        "Archie Comics"
    ], 
    "app_title": "KidsToysToSee"
},{
    "category": "Comics", 
    "description": "  Learn how to draw Manga with some of the finest YouTube tutorial videos. ", 
    "similar_apps": [
        "How to Draw Manga", 
        "Draw Anime - Manga Tutorials", 
        "Draw Cartoons", 
        "Draw Glow Cartoon", 
        "HD Anime wallpapers", 
        "SketchBook - draw and paint", 
        "Anime Girl HD Wallpapers", 
        "Sketch", 
        "Draw Cartoons 2", 
        "How To Draw Anime Manga", 
        "How to Draw 3D and Illusions", 
        "Crunchyroll Manga", 
        "네이버 웹툰 - Naver Webtoon", 
        "How To Draw Manga", 
        "Cartoonist Free - Cartoon, Ani"
    ], 
    "app_title": "DrawShow: Anime Manga Tutorial"
},{
    "category": "Comics", 
    "description": "  Free comics are now available on your mobile devices! ", 
    "similar_apps": [
        "LINE WEBTOON - Free Comics", 
        "다음 웹툰 - Daum Webtoon", 
        "모두의 웹툰", 
        "투믹스 - 웹툰 (무료웹툰/인기만화)", 
        "Spottoon – Premium Comics", 
        "NGOMIK - Baca Komik Indonesia", 
        "DrawShow: Anime Manga Tutorial", 
        "Korean webtoon collection", 
        "케이툰(KTOON) - 무료 웹툰,웹소설", 
        "CIAYO Comics - Free Comics", 
        "만화365 (무료만화 & 무료소설 & 무료웹툰)", 
        "Kolam Komik", 
        "New Komik Lucu Bikin Ngakak", 
        "comico 免費全彩漫畫", 
        "NC COMIX -  Free Game webtoons"
    ], 
    "app_title": "네이버 웹툰 - Naver Webtoon"
},{
    "category": "Comics", 
    "description": "  Teach you how to draw the glow things step-by-step with tutorials! ", 
    "similar_apps": [
        "Draw Glow Flower", 
        "MagiMobile – Mighty Magiswords", 
        "Doodle Magic Mirror Draw! Kids", 
        "Disney Color and Play", 
        "Trippy Draw", 
        "Мульт - детские мультфильмы", 
        "Coloring Book", 
        "Ben 10 MouthOff", 
        "Coloring Book 2017", 
        "ACK Comics", 
        "Gulli – l’appli des enfants", 
        "BLOW mini games for Baby Kids", 
        "Jake's Pirate School", 
        "The Lion Guard"
    ], 
    "app_title": "Draw Glow Cartoon"
},{
    "category": "Comics", 
    "description": "  Genuine mobile phone serial wonderful animated comic novel, updated every day! ", 
    "similar_apps": [
        "漫咖", 
        "漫漫漫画-每日更新免费高清漫画", 
        "LINE WEBTOON - Free Comics", 
        "腾讯动漫", 
        "漫畫神", 
        "GANMA! - 漫画が全話無料で制限ナシのマンガアプリ", 
        "漫本-全球华人原创漫画发行平台", 
        "LINE Manga -正版日本漫畫 每天免費更新！", 
        "コミックエス - 少女漫画/恋愛マンガ 無料で読み放題♪", 
        "ComicScreen - ComicViewer", 
        "COMIDEA    Writing Comics APP", 
        "Comics", 
        "Astonishing Comic Reader", 
        "Marvel Comics", 
        "네이버 웹툰 - Naver Webtoon"
    ], 
    "app_title": "comico 免費全彩漫畫"
},{
    "category": "Comics", 
    "description": "  매일 매일 새로운 네이버 웹툰 ", 
    "similar_apps": [
        "네이버 웹툰 - Naver Webtoon", 
        "comico 免費全彩漫畫", 
        "漫咖", 
        "漫漫漫画-每日更新免费高清漫画", 
        "Comics", 
        "다음 웹툰 - Daum Webtoon", 
        "腾讯动漫", 
        "LINE Manga -正版日本漫畫 每天免費更新！", 
        "CIAYO Comics - Free Comics", 
        "ComicScreen - ComicViewer", 
        "NGOMIK - Baca Komik Indonesia", 
        "Astonishing Comic Reader", 
        "Marvel Comics", 
        "Spottoon – Premium Comics", 
        "Kolam Komik"
    ], 
    "app_title": "LINE WEBTOON - Free Comics"
},{
    "category": "Comics", 
    "description": "  Get Instant Access to over 20,000 digital comics with Marvel Unlimited! ", 
    "similar_apps": [
        "Marvel Unlimited", 
        "Comics", 
        "DC Comics", 
        "Astonishing Comic Reader", 
        "ComicScreen - ComicViewer", 
        "AVENGERS S.T.A.T.I.O.N. MOBILE", 
        "LINE WEBTOON - Free Comics", 
        "Challenger Comics Viewer", 
        "Perfect Viewer", 
        "Mix+Smash: Marvel Mashers", 
        "ComicRack Free", 
        "Dark Horse Comics", 
        "ComiCat (Comic Reader/Viewer)", 
        "comics", 
        "CIAYO Comics - Free Comics"
    ], 
    "app_title": "Marvel Comics"
},{
    "category": "Comics", 
    "description": "  대한민국 웹툰의 기준 투믹스! 매일 업데이트 되는 다양한 웹툰이 가득! 낚시신공2, 총수비기닝, 고교정점, 일진 등 최신 인기 웹툰 독점 연재! ", 
    "similar_apps": [
        "투믹스 - 웹툰 (무료웹툰/인기만화)", 
        "Korean webtoon collection", 
        "케이툰(KTOON) - 무료 웹툰,웹소설", 
        "YO! 웹툰 - 무료 만화/웹툰/커뮤니티/게임/쇼핑!", 
        "네이버 웹툰 - Naver Webtoon", 
        "다음 웹툰 - Daum Webtoon", 
        "버프(BUFF) – 웹툰, 그 이상의 즐거움", 
        "코믹GT Lite -  만화, 웹툰, 소설", 
        "모두의 웹툰", 
        "DrawShow: Anime Manga Tutorial", 
        "만화365 (무료만화 & 무료소설 & 무료웹툰)", 
        "Secret Love - Dating game", 
        "너도나도 애니툰", 
        "Cartoonist Free - Cartoon, Ani", 
        "뿌딩-웹소설,웹툰,만화,로맨스,판타지"
    ], 
    "app_title": "폭스툰 - 구글결제"
},{
    "category": "Comics", 
    "description": "  대한민국 웹툰의 기준 투믹스! 매일 업데이트 되는 다양한 웹툰이 가득! 낚시신공2, 총수비기닝, 고교정점, 일진 등 최신 인기 웹툰 독점 연재! ", 
    "similar_apps": [
        "투믹스 - 웹툰 (무료웹툰/인기만화)", 
        "Lezhin Comics - Daily Releases", 
        "네이버 웹툰 - Naver Webtoon", 
        "모두의 웹툰", 
        "다음 웹툰 - Daum Webtoon", 
        "배틀코믹스 – 덕심자극 무료웹툰, 게임만화!", 
        "케이툰(KTOON) - 무료 웹툰,웹소설", 
        "YO! 웹툰 - 무료 만화/웹툰/커뮤니티/게임/쇼핑!", 
        "만화365 (무료만화 & 무료소설 & 무료웹툰)", 
        "Korean webtoon collection", 
        "comico 免費全彩漫畫", 
        "LINE WEBTOON - Free Comics", 
        "ZzangFunnyComics23", 
        "짱웃긴만화22", 
        "코믹GT Lite -  만화, 웹툰, 소설"
    ], 
    "app_title": "탑툰 - 웹툰/만화를 매일매일 무료"
},{
    "category": "Comics", 
    "description": "  매일 매일 새로운 네이버 웹툰 ", 
    "similar_apps": [
        "네이버 웹툰 - Naver Webtoon", 
        "모두의 웹툰", 
        "다음 웹툰 - Daum Webtoon", 
        "만화365 (무료만화 & 무료소설 & 무료웹툰)", 
        "케이툰(KTOON) - 무료 웹툰,웹소설", 
        "YO! 웹툰 - 무료 만화/웹툰/커뮤니티/게임/쇼핑!", 
        "짱웃긴만화22", 
        "ZzangFunnyComics23", 
        "Korean webtoon collection", 
        "만화만화1", 
        "DrawShow: Anime Manga Tutorial", 
        "코믹GT Lite -  만화, 웹툰, 소설", 
        "ZzangFunnyComics24", 
        "ComicScreen - ComicViewer", 
        "인터넷만화방 만화 웹툰 소설 무료만화 무료소설 무료웹툰"
    ], 
    "app_title": "투믹스 - 웹툰 (무료웹툰/인기만화)"
},{
    "category": "Comics", 
    "description": "  ＼ガンマンが登場するTVCM放映中!!／", 
    "similar_apps": [
        "GANMA! - 漫画が全話無料で制限ナシのマンガアプリ", 
        "コミックエス - 少女漫画/恋愛マンガ 無料で読み放題♪", 
        "【無料マンガ】マンガZERO／国内最大級の無料漫画アプリ", 
        "pixivコミック - みんなの無料マンガアプリ", 
        "マンガBANG！-人気漫画が全巻無料読み放題-", 
        "漫画読破 全巻無料のマンガアプリ", 
        "Manga Box: Manga App", 
        "【無料漫画】みんコミ/マンガ読み放題-美少女ヒロインいっぱい", 
        "マンガ図書館Z　〜3800巻無料・読み放題のコミックアプリ！", 
        "[全巻無料] 奇面組 漫画を無料で読めるマンガコミックアプリ", 
        "完全無料!!スラムダンクの続き(まとめサイト)新着782話", 
        "Chocola-Comic", 
        "[全巻無料] ブラックジャックによろしく", 
        "[無料漫画]本当にあった修羅場の漫画VOL.03", 
        "お絵かき無料漫画広場"
    ], 
    "app_title": "読書のお時間ですビューア"
},{
    "category": "Comics", 
    "description": "  매일 매일 새로운 네이버 웹툰 ", 
    "similar_apps": [
        "네이버 웹툰 - Naver Webtoon", 
        "다음 웹툰 - Daum Webtoon", 
        "투믹스 - 웹툰 (무료웹툰/인기만화)", 
        "모두의 웹툰", 
        "탑툰 - 웹툰/만화를 매일매일 무료", 
        "배틀코믹스 – 덕심자극 무료웹툰, 게임만화!", 
        "케이툰(KTOON) - 무료 웹툰,웹소설", 
        "Korean webtoon collection", 
        "LINE WEBTOON - Free Comics", 
        "YO! 웹툰 - 무료 만화/웹툰/커뮤니티/게임/쇼핑!", 
        "Spottoon – Premium Comics", 
        "DrawShow: Anime Manga Tutorial", 
        "만화365 (무료만화 & 무료소설 & 무료웹툰)", 
        "NGOMIK - Baca Komik Indonesia", 
        "NC COMIX -  Free Game webtoons"
    ], 
    "app_title": "Lezhin Comics - Daily Releases"
},{
    "category": "Comics", 
    "description": "  ＼ガンマンが登場するTVCM放映中!!／", 
    "similar_apps": [
        "GANMA! - 漫画が全話無料で制限ナシのマンガアプリ", 
        "コミックエス - 少女漫画/恋愛マンガ 無料で読み放題♪", 
        "マンガBANG！-人気漫画が全巻無料読み放題-", 
        "pixivコミック - みんなの無料マンガアプリ", 
        "漫画読破 全巻無料のマンガアプリ", 
        "Manga Box: Manga App", 
        "漫漫漫画-每日更新免费高清漫画", 
        "マンガ図書館Z　〜3800巻無料・読み放題のコミックアプリ！", 
        "comico 免費全彩漫畫", 
        "【無料漫画】みんコミ/マンガ読み放題-美少女ヒロインいっぱい", 
        "漫本-全球华人原创漫画发行平台", 
        "漫畫神", 
        "腾讯动漫", 
        "漫咖", 
        "漫饭－随时随地看漫画"
    ], 
    "app_title": "【無料マンガ】マンガZERO／国内最大級の無料漫画アプリ"
},{
    "category": "Comics", 
    "description": "  Over 1,000,000 SPHD Anime & Cartoon Comic Anime Girls HD! ", 
    "similar_apps": [
        "Anime Girls HD", 
        "Anime Girls Cute", 
        "Anime Girls All HD", 
        "Anime Girls HD Wallpaper", 
        "Anime Girls Full HD", 
        "Princess Girl Wallpaper HD", 
        "Anime Girls", 
        "Anime Girls Background", 
        "Anime Girls Pro", 
        "Anime Girls Full", 
        "Anime HD Backgrounds Pro", 
        "Anime Girls Otaku Wallpaper", 
        "Anime Girls Wallpaper", 
        "An Anime Girls", 
        "Anime Girls Wallpaper HD"
    ], 
    "app_title": "Anime Girls Best"
},{
    "category": "Comics", 
    "description": "  we will public about  surprise eggs, play doh, play doh ice cream videos ", 
    "similar_apps": [
        "Doh ToysReview", 
        "kids surprises", 
        "kidsToysReview", 
        "FluffyJetToys", 
        "Crazy Fun Kids", 
        "DisneyCarToys", 
        "Playing Dough Reviews", 
        "Surprise Collector", 
        "Kids Toys", 
        "Kids Toys collection", 
        "PlayToys Review", 
        "Play Toy Surprises", 
        "Surprise Eggs unboxing toys", 
        "Ryan ToysReview Video", 
        "FunToysReview"
    ], 
    "app_title": "FunToyzCollector Kids"
},{
    "category": "Comics", 
    "description": "  Download quickly and have fun wiht friends and family ", 
    "similar_apps": [
        "Lion Sounds", 
        "Siren Sounds", 
        "Diet in 13 days", 
        "How to draw manga", 
        "Birds Sounds", 
        "Gorilla Sounds", 
        "Bees Sounds", 
        "Whale Sounds", 
        "Fly Sounds", 
        "Wolf Sounds", 
        "Cow Sounds", 
        "Donkey Sounds", 
        "Taekwondo", 
        "Bodybuilding program", 
        "Maths"
    ], 
    "app_title": "Lion Sounds"
},{
    "category": "Comics", 
    "description": "  An excellent reader of manga for everyone ", 
    "similar_apps": [
        "Manga Online", 
        "Manga en Español", 
        "Mangi po Polsku", 
        "عرب مانجا", 
        "มังงะไทย", 
        "Manga Indonesia", 
        "Manga Türkçe", 
        "Manga Việt", 
        "Manga Français", 
        "Italiano Manga", 
        "Pусский манга", 
        "Brasil Mangás"
    ], 
    "app_title": "Manga en Español"
},{
    "category": "Comics", 
    "description": "  Of national animation is a quiz app.", 
    "similar_apps": [
        "クイズ for ドラえもん どらえもん ドラエモン アニメ", 
        "漫画セット一気に届く通販サイト「全巻漫画.com」"
    ], 
    "app_title": "KidsTV: How To Draw"
},{
    "category": "Comics", 
    "description": "  Sounds of Zueiras 2 to listen and share in WhatsApp. ", 
    "similar_apps": [
        "Sons das Zueiras 2", 
        "Audio Jokes", 
        "Alô é da Radio", 
        "Fábrica de Zueiras", 
        "Sons Assustadores", 
        "Top Piadas + Aí Paaah Tirinhas", 
        "Animals Zueiras do Zap", 
        "BIRL - Frases de Monstrão", 
        "ZUEIRA Sem Limites App Oficial", 
        "Comics Super Heroes", 
        "Social Comédia", 
        "Vídeos Engraçados - Zueiras", 
        "Mundo da Zueira", 
        "ZUA - Zueiras Whats", 
        "Imagens para WhatsApp"
    ], 
    "app_title": "Sons de Zueira para WhatsApp"
},{
    "category": "Comics", 
    "description": "  Free Doujinshi Yaoi are now available on your mobile devices! ", 
    "similar_apps": [
        "Doujinshi Yaoi Online", 
        "Doujinshi Online - Premium", 
        "animeMANGA Reader for Dōjinshi", 
        "Doujinshi Yaoi Online Premium", 
        "台灣同人通", 
        "ごちうさアラーム～チノ編～", 
        "同人ショップ（D-Stage）", 
        "同人画像集壁紙forSAO", 
        "3000 Truyện Cười Offline", 
        "Truyen Teen Offline", 
        "Tủ Truyện Tranh 360", 
        "MComic Reader", 
        "Tiểu thuyết,truyện tranh", 
        "Truyện tranh: Trạng Quỳnh", 
        "Truyện Cười Vova 2X"
    ], 
    "app_title": "Doujinshi Online"
},{
    "category": "Comics", 
    "description": "  Over 1,000,000 SPHD Anime & Cartoon Comic Anime Girls Cute! ", 
    "similar_apps": [
        "Anime Girls Cute", 
        "Princess Girl Wallpaper HD", 
        "Anime Girls All HD", 
        "Anime Girls HD Wallpaper", 
        "Anime Girls Full HD", 
        "Anime Girls Best", 
        "Anime Girls Pro", 
        "Anime Girls", 
        "Anime Pictures", 
        "Anime Girls Background", 
        "Anime HD Backgrounds Pro", 
        "An Anime Girls", 
        "Anime Girls Full", 
        "Anime Girls Otaku Wallpaper", 
        "Anime Girls Wallpaper"
    ], 
    "app_title": "Anime Girls HD"
},{
    "category": "Comics", 
    "description": "  Over 1,000,000 SPHD Anime & Cartoon Comic Anime Girls Best! ", 
    "similar_apps": [
        "Anime Girls Best", 
        "Anime Girls All HD", 
        "Anime Girls Otaku Wallpaper", 
        "Anime Girls HD", 
        "Anime Girls HD Wallpaper", 
        "Anime Girls Full", 
        "Anime Girls Wallpaper HD", 
        "Anime Girls Full HD", 
        "Anime Girls Cute", 
        "Anime Pictures", 
        "Princess Girl Wallpaper HD", 
        "Anime Girl Wallpaper", 
        "Anime Girls", 
        "Anime HD Backgrounds Pro", 
        "Anime Girls Pro"
    ], 
    "app_title": "Anime Girls Wallpaper"
},{
    "category": "Comics", 
    "description": "  Over 1,000,000 SPHD Anime & Cartoon Comic Anime Girls HD! ", 
    "similar_apps": [
        "Anime Girls HD", 
        "Anime Girl Wallpaper ACG", 
        "Cosplay Girl Wallpaper HD", 
        "Anime Girl Wallpapers HD", 
        "Anime Girl HD Wallpaper", 
        "Cosplay Girl Wallpaper HD", 
        "Mermaid Girl Wallpaper HD", 
        "Anime Girls All HD", 
        "Anime Girls Cute", 
        "Princess Girl Wallpaper HD", 
        "Anime Girls HD Wallpaper", 
        "Anime Girls Best", 
        "Anime Girls Full HD", 
        "Anime Girls", 
        "Anime Girls Pro"
    ], 
    "app_title": "Anime Girls QHD"
},{
    "category": "Comics", 
    "description": "  Free Doujinshi are now available on your mobile devices! ", 
    "similar_apps": [
        "Doujinshi Online", 
        "Doujinshi Online - Premium", 
        "Doujinshi Yaoi Online Premium", 
        "animeMANGA Reader for Dōjinshi", 
        "台灣同人通", 
        "Boys' Love Comic–Cartoon&Anime", 
        "Mangaa Reader", 
        "ごちうさアラーム～チノ編～", 
        "My Lovely Cat (Esp)", 
        "同人ショップ（D-Stage）", 
        "Anime Keyboard Theme", 
        "Amor na Máfia", 
        "同人画像集壁紙forSAO", 
        "Expressive Comic Creator", 
        "BL検定"
    ], 
    "app_title": "Doujinshi Yaoi Online"
},{
    "category": "Comics", 
    "description": "  Kids Videos with Toys & Surprise Eggs! ", 
    "similar_apps": [
        "KidsToysAndMe", 
        "FluffyJetToys", 
        "Superhero & Princess for Kids", 
        "DisneyCarToys", 
        "FunToysReview"
    ], 
    "app_title": "Superhero & Princess Kids IRL"
},{
    "category": "Comics", 
    "description": "  Free comics are now available on your mobile devices! ", 
    "similar_apps": [
        "LINE WEBTOON - Free Comics", 
        "Crunchyroll Manga", 
        "Mangaa Reader", 
        "NGOMIK - Baca Komik Indonesia", 
        "Manga Box: Manga App", 
        "CIAYO Comics - Free Comics", 
        "DrawShow: Anime Manga Tutorial", 
        "Kolam Komik", 
        "Comics", 
        "Comic: Manga Reader-Comic Read", 
        "Bacamanga Lengkap", 
        "Komik Lucu Ngaco 4:Gokil", 
        "How to Draw Manga", 
        "네이버 웹툰 - Naver Webtoon", 
        "ROMANCE"
    ], 
    "app_title": "Baca Manga Komik Indonesia"
},{
    "category": "Comics", 
    "description": "  Convert photo into cartoon and an artwork. ", 
    "similar_apps": [
        "Photo Cartoon", 
        "Cartoon Picture App Filters", 
        "Cartoon,Avatar Maker", 
        "Cartoonist - Cartoon, Comic", 
        "Comicize - the comics maker", 
        "时光机", 
        "葛西西瓜園", 
        "ComiCat (Comic Reader/Viewer)", 
        "How To Draw Manga", 
        "Photo Editor & Stickers:Camera", 
        "Drawing Manga Cartoon", 
        "Comic: Manga Reader-Comic Read", 
        "Magic Photo Painter", 
        "DrawShow Pro: Anime Tutorials", 
        "Anime Girl Pose 3D"
    ], 
    "app_title": "Real Time Cartoon Effect"
},{
    "category": "Comics", 
    "description": "  《新 三國群英傳》8/29正式OB", 
    "similar_apps": [
        "向三國群英致敬(19年經典影片回顧)", 
        "Comic Browser- Cartoon & Anime", 
        "Boys' Love Comic–Cartoon&Anime", 
        "ComiCat (Comic Reader/Viewer)", 
        "Nekollection Manga Reader", 
        "조조전 Cost 계산기", 
        "Anime Manga Drawing", 
        "漫畫神", 
        "Quick Comic Viewer", 
        "comics", 
        "LZ Comic Viewer", 
        "New Comic view(No bottom ads)", 
        "MComic Reader", 
        "COMICポラリス", 
        "Texas Ranger"
    ], 
    "app_title": "Three Kingdoms Comics-Cartoon"
},{
    "category": "Comics", 
    "description": "  Card Maker for YugiOh Duel TCG help duelists create YugiOh cards easily ", 
    "similar_apps": [
        "Card Maker for YugiOh Duel TCG", 
        "HD Anime wallpapers", 
        "Card Maker for Pokemon", 
        "Yugo", 
        "Photo Comics Pro", 
        "Deckmaker for Yu-Gi-Oh!", 
        "Wishlist for YuGiOh! Pro", 
        "YugiDuel: YuGiOh LP Calculator", 
        "Life Counter PRO for YuGiOh", 
        "Comicize", 
        "Lp Counter YuGiOh", 
        "Frameless Comics & GIF Maker", 
        "Comic Creator", 
        "Comicize - the comics maker", 
        "Expressive Comic Creator"
    ], 
    "app_title": "Card Maker for YugiOh Duel TCG"
},{
    "category": "Comics", 
    "description": "  Anime character & avatar with libraries of eyes,eyebrows,haircuts,accessories ", 
    "similar_apps": [
        "Anime Avatar Studio", 
        "Cartoon,Avatar Maker", 
        "Q Avatar (Avatar Maker)", 
        "Factory for Avatar", 
        "Avatar Maker: Anime", 
        "Avatar Maker", 
        "Comic Creator", 
        "Expressive Comic Creator", 
        "Comicize - the comics maker", 
        "Frameless Comics & GIF Maker", 
        "Comic Page Creator", 
        "Comicker -The real comic maker", 
        "Comic Maker for Android", 
        "POP Comics", 
        "Anime Manga Drawing"
    ], 
    "app_title": "Anime Maker"
},{
    "category": "Comics", 
    "description": "  A Comic Artifact for Anime World！ ", 
    "similar_apps": [
        "Comic Browser- Cartoon & Anime", 
        "Boys' Love Comic–Cartoon&Anime", 
        "漫畫神", 
        "COMIDEA    Writing Comics APP", 
        "一画换一画", 
        "Drawing Manga Cartoon", 
        "ComiCat (Comic Reader/Viewer)", 
        "Nekollection Manga Reader", 
        "How To Draw Manga", 
        "陰陽師漫畫大全 - 陰陽師之京都異變、陰陽師漫畫", 
        "Cartoonist - Cartoon, Comic", 
        "DrawShow Pro: Anime Tutorials", 
        "Arar", 
        "Quick Comic Viewer", 
        "comics"
    ], 
    "app_title": "Guns Girl Comics–Cartoon&Anime"
},{
    "category": "Comics", 
    "description": "  This Anime Alone Guy Wallpapers pack contains high quality Full HD wallpapers. ", 
    "similar_apps": [
        "Anime Alone Guy Wallpapers", 
        "Anime Couple Cute Wallpapers", 
        "Anime Sweet Couple in Love", 
        "Love Quotes Wallpapers Locker", 
        "Mydol- Virtual chat, Fanletter", 
        "HD Anime wallpapers", 
        "Anime Girl Live Wallpapers", 
        "Anime Pictures", 
        "Cute Girl Anime Wallpaper HD", 
        "Anime Girl HD Wallpapers", 
        "Birds Wallpaper HD Lockscreen", 
        "Mojim Lyrics", 
        "Wallpapers For Kids", 
        "Cool Wallpapers", 
        "Anime Girl Wallpaper HD"
    ], 
    "app_title": "Anime Little Boy Wallpapers"
},{
    "category": "Comics", 
    "description": "  Genuine mobile phone serial wonderful animated comic novel, updated every day! ", 
    "similar_apps": [
        "漫咖", 
        "comico 免費全彩漫畫", 
        "漫漫漫画-每日更新免费高清漫画", 
        "腾讯动漫", 
        "漫本-全球华人原创漫画发行平台", 
        "LINE Manga -正版日本漫畫 每天免費更新！", 
        "GANMA! - 漫画が全話無料で制限ナシのマンガアプリ", 
        "コミックエス - 少女漫画/恋愛マンガ 無料で読み放題♪", 
        "极速漫画——免费看超有料的二次元阅读APP", 
        "COMIDEA    Writing Comics APP", 
        "Perfect Viewer", 
        "台灣同人通", 
        "マンガ図書館Z　〜3800巻無料・読み放題のコミックアプリ！", 
        "Quick Comic Viewer", 
        "陰陽師漫畫大全 - 陰陽師之京都異變、陰陽師漫畫"
    ], 
    "app_title": "漫畫神"
},{
    "category": "Comics", 
    "description": "  漫漫漫画，与优秀漫画作者倾情联袂，秉承正版原创，坚持每日首发，给你有笑意的条漫，有诚意的绘本，有新意的专题，最好不要错过。 ", 
    "similar_apps": [
        "漫漫漫画-每日更新免费高清漫画", 
        "comico 免費全彩漫畫", 
        "腾讯动漫", 
        "漫咖", 
        "漫畫神", 
        "GANMA! - 漫画が全話無料で制限ナシのマンガアプリ", 
        "LINE Manga -正版日本漫畫 每天免費更新！", 
        "コミックエス - 少女漫画/恋愛マンガ 無料で読み放題♪", 
        "极速漫画——免费看超有料的二次元阅读APP", 
        "COMIDEA    Writing Comics APP", 
        "台灣同人通", 
        "マンガ図書館Z　〜3800巻無料・読み放題のコミックアプリ！", 
        "陰陽師漫畫大全 - 陰陽師之京都異變、陰陽師漫畫", 
        "Boys' Love Comic–Cartoon&Anime", 
        "【無料漫画】みんコミ/マンガ読み放題-美少女ヒロインいっぱい"
    ], 
    "app_title": "漫本-全球华人原创漫画发行平台"
},{
    "category": "Comics", 
    "description": "  Genuine mobile phone serial wonderful animated comic novel, updated every day! ", 
    "similar_apps": [
        "漫咖", 
        "comico 免費全彩漫畫", 
        "腾讯动漫", 
        "漫漫漫画-每日更新免费高清漫画", 
        "漫饭－随时随地看漫画", 
        "Manga Box: Manga App", 
        "漫畫神", 
        "漫本-全球华人原创漫画发行平台", 
        "LINE Manga -正版日本漫畫 每天免費更新！", 
        "邪恶漫画", 
        "嗨漫画", 
        "GANMA! - 漫画が全話無料で制限ナシのマンガアプリ", 
        "乐看动漫", 
        "Comics4Me", 
        "超次元新番"
    ], 
    "app_title": "動漫屋——快來免費閱讀漫畫、動畫"
},{
    "category": "Comics", 
    "description": "  toy review for toddlers,babies, infants,Pixar, Nickelodeon, Play Doh, Claymation ", 
    "similar_apps": [
        "FunToyzCollector", 
        "KidsSurpriseFun", 
        "kidsToysReview", 
        "Surprise Collector", 
        "FluffyJetToys", 
        "Crazy Fun Kids", 
        "PLAYDOHCards by Shuffle", 
        "DisneyCarToys", 
        "Dough Toys", 
        "kids surprises", 
        "Playing Dough Reviews", 
        "Toys And Me", 
        "ToyScouter Fans", 
        "Superhero Fun Kids Stop Motion", 
        "Kids Toys"
    ], 
    "app_title": "Doh ToysReview"
},{
    "category": "Comics", 
    "description": "  Action, Adventure, in which blood Comics", 
    "similar_apps": [
        "comico 免費全彩漫畫", 
        "漫咖", 
        "LINE WEBTOON - Free Comics", 
        "漫畫神", 
        "腾讯动漫", 
        "GANMA! - 漫画が全話無料で制限ナシのマンガアプリ", 
        "漫本-全球华人原创漫画发行平台", 
        "LINE Manga -正版日本漫畫 每天免費更新！", 
        "コミックエス - 少女漫画/恋愛マンガ 無料で読み放題♪", 
        "COMIDEA    Writing Comics APP", 
        "极速漫画——免费看超有料的二次元阅读APP", 
        "マンガ図書館Z　〜3800巻無料・読み放題のコミックアプリ！", 
        "네이버 웹툰 - Naver Webtoon", 
        "台灣同人通", 
        "Boys' Love Comic–Cartoon&Anime"
    ], 
    "app_title": "漫漫漫画-每日更新免费高清漫画"
},{
    "category": "Comics", 
    "description": "  Genuine mobile phone serial wonderful animated comic novel, updated every day! ", 
    "similar_apps": [
        "漫咖", 
        "漫畫神", 
        "Quick Comic Viewer", 
        "comics", 
        "LZ Comic Viewer", 
        "腾讯动漫", 
        "Boys' Love Comic–Cartoon&Anime", 
        "New Comic view(No bottom ads)", 
        "漫漫漫画-每日更新免费高清漫画", 
        "ComiCat (Comic Reader/Viewer)", 
        "动漫资料库", 
        "Anime Manga Drawing", 
        "陰陽師漫畫大全 - 陰陽師之京都異變、陰陽師漫畫", 
        "Anime & Gift card", 
        "aniComic"
    ], 
    "app_title": "Comic Browser- Cartoon & Anime"
},{
    "category": "Comics", 
    "description": "  Tool for drawing poses and to study the light of manga girl characters ", 
    "similar_apps": [
        "Anime Girl Pose 3D", 
        "Handy Art Reference Tool", 
        "TiPose 3d human pose tool", 
        "ProNamaChan Pose Lite", 
        "Anime Pose 3D", 
        "Horse Pose Tool 3D", 
        "DrawShow: Anime Manga Tutorial", 
        "ComiCat (Comic Reader/Viewer)", 
        "Cat Pose Tool 3D", 
        "ProNamaChan Pose", 
        "ComicScreen - ComicViewer", 
        "DrawShow Pro: Anime Tutorials", 
        "네이버 웹툰 - Naver Webtoon", 
        "Draw Glow Cartoon", 
        "Perfect Viewer"
    ], 
    "app_title": "Pose Tool 3D"
},{
    "category": "Comics", 
    "description": "  最强二次元结界，热门漫画免费看，流行动画看不停！火影忍者、海贼王、尸兄、惊奇先生、尸兄、中国惊奇先生、斗破苍穹、龙珠”等动画动漫任你挑选。 ", 
    "similar_apps": [
        "腾讯动漫", 
        "Boys' Love Comic–Cartoon&Anime", 
        "漫漫漫画-每日更新免费高清漫画", 
        "漫咖", 
        "漫饭－随时随地看漫画", 
        "漫本-全球华人原创漫画发行平台", 
        "邪恶漫画", 
        "嗨漫画", 
        "動漫屋——快來免費閱讀漫畫、動畫", 
        "乐看动漫", 
        "Comics4Me", 
        "极速漫画——免费看超有料的二次元阅读APP", 
        "超次元新番", 
        "多看漫画——多看优质免费的漫画", 
        "陰陽師漫畫大全 - 陰陽師之京都異變、陰陽師漫畫"
    ], 
    "app_title": "可米酷漫画-耽美.热血.恐怖.少女.搞笑.免费漫画.快看不停"
},{
    "category": "Comics", 
    "description": "  This application will enable donated users only function in Perfect Viewer. ", 
    "similar_apps": [
        "Perfect Viewer Donation", 
        "Perfect Viewer", 
        "Perfect Viewer PDF&DJVU Plugin", 
        "Perfect Viewer Source Plugin", 
        "ComicScreen - ComicViewer", 
        "ComiCat (Comic Reader/Viewer)", 
        "Challenger Comics Viewer", 
        "Bubble", 
        "Comics Reader: CBR, CBZ, PDF", 
        "Astonishing Comic Reader", 
        "Marvel Comics", 
        "Maru", 
        "ComicRack", 
        "Pose Tool 3D", 
        "Challenger Viewer Donation"
    ], 
    "app_title": "Perfect Viewer Donation 2"
}
]